performance/__init__.py
performance/__main__.py
performance/rating.py
player_performance-0.3.0.dist-info/LICENSE
player_performance-0.3.0.dist-info/METADATA
player_performance-0.3.0.dist-info/WHEEL
player_performance-0.3.0.dist-info/entry_points.txt
player_performance-0.3.0.dist-info/top_level.txt
player_performance-0.3.0.dist-info/RECORD
