Metadata-Version: 2.1
Name: player-performance
Version: 0.3.0
Summary: Gets the player performance and rating change from the tournament.
Home-page: https://github.com/fsmosca/player-performance
Author: Ferdinand Mosca
Author-email: ferdymosca@gmail.com
Project-URL: Bug Tracker, https://github.com/fsmosca/player-performance/issues
Classifier: Programming Language :: Python :: 3
Classifier: License :: OSI Approved :: GNU General Public License v3 (GPLv3)
Classifier: Operating System :: OS Independent
Classifier: Development Status :: 4 - Beta
Classifier: Intended Audience :: Developers
Classifier: Intended Audience :: End Users/Desktop
Classifier: Intended Audience :: Science/Research
Requires-Python: >=3.7
License-File: LICENSE
Requires-Dist: chess (==1.9.1)
Requires-Dist: pandas
